[ {
  "@id" : "_:genid1",
  "@type" : [ "http://www.w3.org/2002/07/owl#Restriction" ],
  "http://www.w3.org/2002/07/owl#onProperty" : [ {
    "@id" : "http://www.semanticweb.org/badr/ontologies/2020/3/untitled-ontology-32#hasMember"
  } ],
  "http://www.w3.org/2002/07/owl#someValuesFrom" : [ {
    "@id" : "http://www.semanticweb.org/badr/ontologies/2020/3/untitled-ontology-32#Person"
  } ]
}, {
  "@id" : "_:genid10",
  "@type" : [ "http://www.w3.org/2002/07/owl#Restriction" ],
  "http://www.w3.org/2002/07/owl#onProperty" : [ {
    "@id" : "http://www.semanticweb.org/badr/ontologies/2020/3/untitled-ontology-32#isPublisherOf"
  } ],
  "http://www.w3.org/2002/07/owl#someValuesFrom" : [ {
    "@id" : "http://www.semanticweb.org/badr/ontologies/2020/3/untitled-ontology-32#Journal"
  } ]
}, {
  "@id" : "_:genid11",
  "@type" : [ "http://www.w3.org/2002/07/owl#Restriction" ],
  "http://www.w3.org/2002/07/owl#onDataRange" : [ {
    "@id" : "http://www.w3.org/2001/XMLSchema#string"
  } ],
  "http://www.w3.org/2002/07/owl#onProperty" : [ {
    "@id" : "http://www.semanticweb.org/badr/ontologies/2020/3/untitled-ontology-32#hasLocationName"
  } ],
  "http://www.w3.org/2002/07/owl#qualifiedCardinality" : [ {
    "@type" : "http://www.w3.org/2001/XMLSchema#nonNegativeInteger",
    "@value" : "1"
  } ]
}, {
  "@id" : "_:genid12",
  "@type" : [ "http://www.w3.org/2002/07/owl#Restriction" ],
  "http://www.w3.org/2002/07/owl#onProperty" : [ {
    "@id" : "http://www.semanticweb.org/badr/ontologies/2020/3/untitled-ontology-32#hasAffiliation"
  } ],
  "http://www.w3.org/2002/07/owl#someValuesFrom" : [ {
    "@id" : "http://www.semanticweb.org/badr/ontologies/2020/3/untitled-ontology-32#Affiliation"
  } ]
}, {
  "@id" : "_:genid13",
  "@type" : [ "http://www.w3.org/2002/07/owl#Restriction" ],
  "http://www.w3.org/2002/07/owl#onProperty" : [ {
    "@id" : "http://www.semanticweb.org/badr/ontologies/2020/3/untitled-ontology-32#isOneOf"
  } ],
  "http://www.w3.org/2002/07/owl#someValuesFrom" : [ {
    "@id" : "http://www.semanticweb.org/badr/ontologies/2020/3/untitled-ontology-32#Publication"
  } ]
}, {
  "@id" : "_:genid14",
  "@type" : [ "http://www.w3.org/2002/07/owl#Restriction" ],
  "http://www.w3.org/2002/07/owl#onDataRange" : [ {
    "@id" : "http://www.w3.org/2001/XMLSchema#string"
  } ],
  "http://www.w3.org/2002/07/owl#onProperty" : [ {
    "@id" : "http://www.semanticweb.org/badr/ontologies/2020/3/untitled-ontology-32#hasAName"
  } ],
  "http://www.w3.org/2002/07/owl#qualifiedCardinality" : [ {
    "@type" : "http://www.w3.org/2001/XMLSchema#nonNegativeInteger",
    "@value" : "1"
  } ]
}, {
  "@id" : "_:genid15",
  "@type" : [ "http://www.w3.org/2002/07/owl#Restriction" ],
  "http://www.w3.org/2002/07/owl#maxQualifiedCardinality" : [ {
    "@type" : "http://www.w3.org/2001/XMLSchema#nonNegativeInteger",
    "@value" : "1"
  } ],
  "http://www.w3.org/2002/07/owl#onDataRange" : [ {
    "@id" : "http://www.w3.org/2001/XMLSchema#string"
  } ],
  "http://www.w3.org/2002/07/owl#onProperty" : [ {
    "@id" : "http://www.semanticweb.org/badr/ontologies/2020/3/untitled-ontology-32#hasORCID"
  } ]
}, {
  "@id" : "_:genid16",
  "@type" : [ "http://www.w3.org/2002/07/owl#Restriction" ],
  "http://www.w3.org/2002/07/owl#onProperty" : [ {
    "@id" : "http://www.semanticweb.org/badr/ontologies/2020/3/untitled-ontology-32#isPublished"
  } ],
  "http://www.w3.org/2002/07/owl#someValuesFrom" : [ {
    "@id" : "http://www.semanticweb.org/badr/ontologies/2020/3/untitled-ontology-32#Journal"
  } ]
}, {
  "@id" : "_:genid17",
  "@type" : [ "http://www.w3.org/2002/07/owl#Restriction" ],
  "http://www.w3.org/2002/07/owl#onDataRange" : [ {
    "@id" : "http://www.w3.org/2001/XMLSchema#dateTime"
  } ],
  "http://www.w3.org/2002/07/owl#onProperty" : [ {
    "@id" : "http://www.semanticweb.org/badr/ontologies/2020/3/untitled-ontology-32#hasDate"
  } ],
  "http://www.w3.org/2002/07/owl#qualifiedCardinality" : [ {
    "@type" : "http://www.w3.org/2001/XMLSchema#nonNegativeInteger",
    "@value" : "1"
  } ]
}, {
  "@id" : "_:genid18",
  "@type" : [ "http://www.w3.org/2002/07/owl#Restriction" ],
  "http://www.w3.org/2002/07/owl#onDataRange" : [ {
    "@id" : "http://www.w3.org/2001/XMLSchema#string"
  } ],
  "http://www.w3.org/2002/07/owl#onProperty" : [ {
    "@id" : "http://www.semanticweb.org/badr/ontologies/2020/3/untitled-ontology-32#hasTitle"
  } ],
  "http://www.w3.org/2002/07/owl#qualifiedCardinality" : [ {
    "@type" : "http://www.w3.org/2001/XMLSchema#nonNegativeInteger",
    "@value" : "1"
  } ]
}, {
  "@id" : "_:genid19",
  "@type" : [ "http://www.w3.org/2002/07/owl#Restriction" ],
  "http://www.w3.org/2002/07/owl#maxQualifiedCardinality" : [ {
    "@type" : "http://www.w3.org/2001/XMLSchema#nonNegativeInteger",
    "@value" : "1"
  } ],
  "http://www.w3.org/2002/07/owl#onDataRange" : [ {
    "@id" : "http://www.w3.org/2001/XMLSchema#string"
  } ],
  "http://www.w3.org/2002/07/owl#onProperty" : [ {
    "@id" : "http://www.semanticweb.org/badr/ontologies/2020/3/untitled-ontology-32#hasDOI"
  } ]
}, {
  "@id" : "_:genid2",
  "@type" : [ "http://www.w3.org/2002/07/owl#Restriction" ],
  "http://www.w3.org/2002/07/owl#onDataRange" : [ {
    "@id" : "http://www.w3.org/2001/XMLSchema#string"
  } ],
  "http://www.w3.org/2002/07/owl#onProperty" : [ {
    "@id" : "http://www.semanticweb.org/badr/ontologies/2020/3/untitled-ontology-32#hasAffiliationName"
  } ],
  "http://www.w3.org/2002/07/owl#qualifiedCardinality" : [ {
    "@type" : "http://www.w3.org/2001/XMLSchema#nonNegativeInteger",
    "@value" : "1"
  } ]
}, {
  "@id" : "_:genid20",
  "@type" : [ "http://www.w3.org/2002/07/owl#Restriction" ],
  "http://www.w3.org/2002/07/owl#maxQualifiedCardinality" : [ {
    "@type" : "http://www.w3.org/2001/XMLSchema#nonNegativeInteger",
    "@value" : "1"
  } ],
  "http://www.w3.org/2002/07/owl#onDataRange" : [ {
    "@id" : "http://www.w3.org/2001/XMLSchema#string"
  } ],
  "http://www.w3.org/2002/07/owl#onProperty" : [ {
    "@id" : "http://www.semanticweb.org/badr/ontologies/2020/3/untitled-ontology-32#hasKey"
  } ]
}, {
  "@id" : "_:genid21",
  "@type" : [ "http://www.w3.org/2002/07/owl#Restriction" ],
  "http://www.w3.org/2002/07/owl#onProperty" : [ {
    "@id" : "http://www.semanticweb.org/badr/ontologies/2020/3/untitled-ontology-32#hasAPublisher"
  } ],
  "http://www.w3.org/2002/07/owl#someValuesFrom" : [ {
    "@id" : "http://www.semanticweb.org/badr/ontologies/2020/3/untitled-ontology-32#Journal"
  } ]
}, {
  "@id" : "_:genid22",
  "@type" : [ "http://www.w3.org/2002/07/owl#Restriction" ],
  "http://www.w3.org/2002/07/owl#onDataRange" : [ {
    "@id" : "http://www.w3.org/2001/XMLSchema#string"
  } ],
  "http://www.w3.org/2002/07/owl#onProperty" : [ {
    "@id" : "http://www.semanticweb.org/badr/ontologies/2020/3/untitled-ontology-32#hasPublisherName"
  } ],
  "http://www.w3.org/2002/07/owl#qualifiedCardinality" : [ {
    "@type" : "http://www.w3.org/2001/XMLSchema#nonNegativeInteger",
    "@value" : "1"
  } ]
}, {
  "@id" : "_:genid23",
  "@type" : [ "http://www.w3.org/2002/07/owl#AllDisjointClasses" ],
  "http://www.w3.org/2002/07/owl#members" : [ {
    "@list" : [ {
      "@id" : "http://www.semanticweb.org/badr/ontologies/2020/3/untitled-ontology-32#Affiliation"
    }, {
      "@id" : "http://www.semanticweb.org/badr/ontologies/2020/3/untitled-ontology-32#Conference"
    }, {
      "@id" : "http://www.semanticweb.org/badr/ontologies/2020/3/untitled-ontology-32#Journal"
    }, {
      "@id" : "http://www.semanticweb.org/badr/ontologies/2020/3/untitled-ontology-32#Location"
    }, {
      "@id" : "http://www.semanticweb.org/badr/ontologies/2020/3/untitled-ontology-32#Publication"
    } ]
  } ]
}, {
  "@id" : "_:genid29",
  "@type" : [ "http://www.w3.org/2002/07/owl#AllDisjointClasses" ],
  "http://www.w3.org/2002/07/owl#members" : [ {
    "@list" : [ {
      "@id" : "http://www.semanticweb.org/badr/ontologies/2020/3/untitled-ontology-32#Affiliation"
    }, {
      "@id" : "http://www.semanticweb.org/badr/ontologies/2020/3/untitled-ontology-32#Conference"
    }, {
      "@id" : "http://www.semanticweb.org/badr/ontologies/2020/3/untitled-ontology-32#Journal"
    }, {
      "@id" : "http://www.semanticweb.org/badr/ontologies/2020/3/untitled-ontology-32#Person"
    }, {
      "@id" : "http://www.semanticweb.org/badr/ontologies/2020/3/untitled-ontology-32#Publication"
    } ]
  } ]
}, {
  "@id" : "_:genid3",
  "@type" : [ "http://www.w3.org/2002/07/owl#Restriction" ],
  "http://www.w3.org/2002/07/owl#onClass" : [ {
    "@id" : "http://www.semanticweb.org/badr/ontologies/2020/3/untitled-ontology-32#Person"
  } ],
  "http://www.w3.org/2002/07/owl#onProperty" : [ {
    "@id" : "http://www.semanticweb.org/badr/ontologies/2020/3/untitled-ontology-32#hasParticipant"
  } ],
  "http://www.w3.org/2002/07/owl#qualifiedCardinality" : [ {
    "@type" : "http://www.w3.org/2001/XMLSchema#nonNegativeInteger",
    "@value" : "1"
  } ]
}, {
  "@id" : "_:genid35",
  "@type" : [ "http://www.w3.org/2002/07/owl#AllDisjointClasses" ],
  "http://www.w3.org/2002/07/owl#members" : [ {
    "@list" : [ {
      "@id" : "http://www.semanticweb.org/badr/ontologies/2020/3/untitled-ontology-32#Affiliation"
    }, {
      "@id" : "http://www.semanticweb.org/badr/ontologies/2020/3/untitled-ontology-32#Conference"
    }, {
      "@id" : "http://www.semanticweb.org/badr/ontologies/2020/3/untitled-ontology-32#Journal"
    }, {
      "@id" : "http://www.semanticweb.org/badr/ontologies/2020/3/untitled-ontology-32#Person"
    }, {
      "@id" : "http://www.semanticweb.org/badr/ontologies/2020/3/untitled-ontology-32#Publication"
    }, {
      "@id" : "http://www.semanticweb.org/badr/ontologies/2020/3/untitled-ontology-32#publisher"
    } ]
  } ]
}, {
  "@id" : "_:genid4",
  "@type" : [ "http://www.w3.org/2002/07/owl#Restriction" ],
  "http://www.w3.org/2002/07/owl#onDataRange" : [ {
    "@id" : "http://www.w3.org/2001/XMLSchema#string"
  } ],
  "http://www.w3.org/2002/07/owl#onProperty" : [ {
    "@id" : "http://www.semanticweb.org/badr/ontologies/2020/3/untitled-ontology-32#hasConferenceName"
  } ],
  "http://www.w3.org/2002/07/owl#qualifiedCardinality" : [ {
    "@type" : "http://www.w3.org/2001/XMLSchema#nonNegativeInteger",
    "@value" : "1"
  } ]
}, {
  "@id" : "_:genid5",
  "@type" : [ "http://www.w3.org/2002/07/owl#Restriction" ],
  "http://www.w3.org/2002/07/owl#onDataRange" : [ {
    "@id" : "http://www.w3.org/2001/XMLSchema#dateTime"
  } ],
  "http://www.w3.org/2002/07/owl#onProperty" : [ {
    "@id" : "http://www.semanticweb.org/badr/ontologies/2020/3/untitled-ontology-32#hasDate"
  } ],
  "http://www.w3.org/2002/07/owl#qualifiedCardinality" : [ {
    "@type" : "http://www.w3.org/2001/XMLSchema#nonNegativeInteger",
    "@value" : "1"
  } ]
}, {
  "@id" : "_:genid6",
  "@type" : [ "http://www.w3.org/2002/07/owl#Restriction" ],
  "http://www.w3.org/2002/07/owl#onDataRange" : [ {
    "@id" : "http://www.w3.org/2001/XMLSchema#string"
  } ],
  "http://www.w3.org/2002/07/owl#onProperty" : [ {
    "@id" : "http://www.semanticweb.org/badr/ontologies/2020/3/untitled-ontology-32#hasLocationName"
  } ],
  "http://www.w3.org/2002/07/owl#qualifiedCardinality" : [ {
    "@type" : "http://www.w3.org/2001/XMLSchema#nonNegativeInteger",
    "@value" : "1"
  } ]
}, {
  "@id" : "_:genid7",
  "@type" : [ "http://www.w3.org/2002/07/owl#Restriction" ],
  "http://www.w3.org/2002/07/owl#onProperty" : [ {
    "@id" : "http://www.semanticweb.org/badr/ontologies/2020/3/untitled-ontology-32#hasPublished"
  } ],
  "http://www.w3.org/2002/07/owl#someValuesFrom" : [ {
    "@id" : "http://www.semanticweb.org/badr/ontologies/2020/3/untitled-ontology-32#Publication"
  } ]
}, {
  "@id" : "_:genid8",
  "@type" : [ "http://www.w3.org/2002/07/owl#Restriction" ],
  "http://www.w3.org/2002/07/owl#onClass" : [ {
    "@id" : "http://www.semanticweb.org/badr/ontologies/2020/3/untitled-ontology-32#publisher"
  } ],
  "http://www.w3.org/2002/07/owl#onProperty" : [ {
    "@id" : "http://www.semanticweb.org/badr/ontologies/2020/3/untitled-ontology-32#hasAPublisher"
  } ],
  "http://www.w3.org/2002/07/owl#qualifiedCardinality" : [ {
    "@type" : "http://www.w3.org/2001/XMLSchema#nonNegativeInteger",
    "@value" : "1"
  } ]
}, {
  "@id" : "_:genid9",
  "@type" : [ "http://www.w3.org/2002/07/owl#Restriction" ],
  "http://www.w3.org/2002/07/owl#onDataRange" : [ {
    "@id" : "http://www.w3.org/2001/XMLSchema#string"
  } ],
  "http://www.w3.org/2002/07/owl#onProperty" : [ {
    "@id" : "http://www.semanticweb.org/badr/ontologies/2020/3/untitled-ontology-32#hasJournalName"
  } ],
  "http://www.w3.org/2002/07/owl#qualifiedCardinality" : [ {
    "@type" : "http://www.w3.org/2001/XMLSchema#nonNegativeInteger",
    "@value" : "1"
  } ]
}, {
  "@id" : "http://www.semanticweb.org/badr/ontologies/2020/3/untitled-ontology-32",
  "@type" : [ "http://www.w3.org/2002/07/owl#Ontology" ]
}, {
  "@id" : "http://www.semanticweb.org/badr/ontologies/2020/3/untitled-ontology-32#Affiliation",
  "@type" : [ "http://www.w3.org/2002/07/owl#Class" ],
  "http://www.w3.org/2000/01/rdf-schema#subClassOf" : [ {
    "@id" : "_:genid1"
  }, {
    "@id" : "_:genid2"
  } ]
}, {
  "@id" : "http://www.semanticweb.org/badr/ontologies/2020/3/untitled-ontology-32#Author",
  "@type" : [ "http://www.w3.org/2002/07/owl#Class" ],
  "http://www.w3.org/2000/01/rdf-schema#subClassOf" : [ {
    "@id" : "http://www.semanticweb.org/badr/ontologies/2020/3/untitled-ontology-32#Person"
  } ]
}, {
  "@id" : "http://www.semanticweb.org/badr/ontologies/2020/3/untitled-ontology-32#Conference",
  "@type" : [ "http://www.w3.org/2002/07/owl#Class" ],
  "http://www.w3.org/2000/01/rdf-schema#subClassOf" : [ {
    "@id" : "_:genid3"
  }, {
    "@id" : "_:genid4"
  }, {
    "@id" : "_:genid5"
  }, {
    "@id" : "_:genid6"
  } ]
}, {
  "@id" : "http://www.semanticweb.org/badr/ontologies/2020/3/untitled-ontology-32#Journal",
  "@type" : [ "http://www.w3.org/2002/07/owl#Class" ],
  "http://www.w3.org/2000/01/rdf-schema#subClassOf" : [ {
    "@id" : "_:genid7"
  }, {
    "@id" : "_:genid8"
  }, {
    "@id" : "_:genid9"
  } ]
}, {
  "@id" : "http://www.semanticweb.org/badr/ontologies/2020/3/untitled-ontology-32#Location",
  "@type" : [ "http://www.w3.org/2002/07/owl#Class" ],
  "http://www.w3.org/2000/01/rdf-schema#subClassOf" : [ {
    "@id" : "_:genid10"
  }, {
    "@id" : "_:genid11"
  } ]
}, {
  "@id" : "http://www.semanticweb.org/badr/ontologies/2020/3/untitled-ontology-32#Person",
  "@type" : [ "http://www.w3.org/2002/07/owl#Class" ],
  "http://www.w3.org/2000/01/rdf-schema#comment" : [ {
    "@value" : "who write or wrote scientific publication"
  } ],
  "http://www.w3.org/2000/01/rdf-schema#subClassOf" : [ {
    "@id" : "_:genid12"
  }, {
    "@id" : "_:genid13"
  }, {
    "@id" : "_:genid14"
  }, {
    "@id" : "_:genid15"
  } ]
}, {
  "@id" : "http://www.semanticweb.org/badr/ontologies/2020/3/untitled-ontology-32#Publication",
  "@type" : [ "http://www.w3.org/2002/07/owl#Class" ],
  "http://www.w3.org/2000/01/rdf-schema#subClassOf" : [ {
    "@id" : "_:genid16"
  }, {
    "@id" : "_:genid17"
  }, {
    "@id" : "_:genid18"
  }, {
    "@id" : "_:genid19"
  }, {
    "@id" : "_:genid20"
  } ]
}, {
  "@id" : "http://www.semanticweb.org/badr/ontologies/2020/3/untitled-ontology-32#hasAName",
  "@type" : [ "http://www.w3.org/2002/07/owl#DatatypeProperty", "http://www.w3.org/2002/07/owl#FunctionalProperty" ],
  "http://www.w3.org/2000/01/rdf-schema#comment" : [ {
    "@value" : "a Person has  a Name"
  } ],
  "http://www.w3.org/2000/01/rdf-schema#domain" : [ {
    "@id" : "http://www.semanticweb.org/badr/ontologies/2020/3/untitled-ontology-32#Person"
  } ],
  "http://www.w3.org/2000/01/rdf-schema#range" : [ {
    "@id" : "http://www.w3.org/2001/XMLSchema#string"
  } ],
  "http://www.w3.org/2000/01/rdf-schema#subPropertyOf" : [ {
    "@id" : "http://www.w3.org/2002/07/owl#topDataProperty"
  } ]
}, {
  "@id" : "http://www.semanticweb.org/badr/ontologies/2020/3/untitled-ontology-32#hasAPublisher",
  "@type" : [ "http://www.w3.org/2002/07/owl#ObjectProperty", "http://www.w3.org/2002/07/owl#FunctionalProperty", "http://www.w3.org/2002/07/owl#AsymmetricProperty", "http://www.w3.org/2002/07/owl#IrreflexiveProperty" ],
  "http://www.w3.org/2000/01/rdf-schema#comment" : [ {
    "@value" : "a journal is publisher by a publisher"
  } ],
  "http://www.w3.org/2000/01/rdf-schema#domain" : [ {
    "@id" : "http://www.semanticweb.org/badr/ontologies/2020/3/untitled-ontology-32#Journal"
  } ],
  "http://www.w3.org/2000/01/rdf-schema#range" : [ {
    "@id" : "http://www.semanticweb.org/badr/ontologies/2020/3/untitled-ontology-32#publisher"
  } ],
  "http://www.w3.org/2000/01/rdf-schema#subPropertyOf" : [ {
    "@id" : "http://www.w3.org/2002/07/owl#topObjectProperty"
  } ],
  "http://www.w3.org/2002/07/owl#inverseOf" : [ {
    "@id" : "http://www.semanticweb.org/badr/ontologies/2020/3/untitled-ontology-32#isPublisherOf"
  } ]
}, {
  "@id" : "http://www.semanticweb.org/badr/ontologies/2020/3/untitled-ontology-32#hasAffiliation",
  "@type" : [ "http://www.w3.org/2002/07/owl#ObjectProperty", "http://www.w3.org/2002/07/owl#AsymmetricProperty", "http://www.w3.org/2002/07/owl#IrreflexiveProperty" ],
  "http://www.w3.org/2000/01/rdf-schema#comment" : [ {
    "@value" : "an Author is affiliated to an Affiliation"
  } ],
  "http://www.w3.org/2000/01/rdf-schema#domain" : [ {
    "@id" : "http://www.semanticweb.org/badr/ontologies/2020/3/untitled-ontology-32#Person"
  } ],
  "http://www.w3.org/2000/01/rdf-schema#range" : [ {
    "@id" : "http://www.semanticweb.org/badr/ontologies/2020/3/untitled-ontology-32#Affiliation"
  } ],
  "http://www.w3.org/2000/01/rdf-schema#subPropertyOf" : [ {
    "@id" : "http://www.w3.org/2002/07/owl#topObjectProperty"
  } ],
  "http://www.w3.org/2002/07/owl#inverseOf" : [ {
    "@id" : "http://www.semanticweb.org/badr/ontologies/2020/3/untitled-ontology-32#hasMember"
  } ]
}, {
  "@id" : "http://www.semanticweb.org/badr/ontologies/2020/3/untitled-ontology-32#hasAffiliationName",
  "@type" : [ "http://www.w3.org/2002/07/owl#DatatypeProperty", "http://www.w3.org/2002/07/owl#FunctionalProperty" ],
  "http://www.w3.org/2000/01/rdf-schema#comment" : [ {
    "@value" : "an affiliation has a name"
  } ],
  "http://www.w3.org/2000/01/rdf-schema#domain" : [ {
    "@id" : "http://www.semanticweb.org/badr/ontologies/2020/3/untitled-ontology-32#Affiliation"
  } ],
  "http://www.w3.org/2000/01/rdf-schema#range" : [ {
    "@id" : "http://www.w3.org/2001/XMLSchema#string"
  } ],
  "http://www.w3.org/2000/01/rdf-schema#subPropertyOf" : [ {
    "@id" : "http://www.w3.org/2002/07/owl#topDataProperty"
  } ]
}, {
  "@id" : "http://www.semanticweb.org/badr/ontologies/2020/3/untitled-ontology-32#hasConferenceName",
  "@type" : [ "http://www.w3.org/2002/07/owl#DatatypeProperty", "http://www.w3.org/2002/07/owl#FunctionalProperty" ],
  "http://www.w3.org/2000/01/rdf-schema#comment" : [ {
    "@value" : "a Conference has a Name"
  } ],
  "http://www.w3.org/2000/01/rdf-schema#domain" : [ {
    "@id" : "http://www.semanticweb.org/badr/ontologies/2020/3/untitled-ontology-32#Conference"
  } ],
  "http://www.w3.org/2000/01/rdf-schema#range" : [ {
    "@id" : "http://www.w3.org/2001/XMLSchema#string"
  } ],
  "http://www.w3.org/2000/01/rdf-schema#subPropertyOf" : [ {
    "@id" : "http://www.w3.org/2002/07/owl#topDataProperty"
  } ]
}, {
  "@id" : "http://www.semanticweb.org/badr/ontologies/2020/3/untitled-ontology-32#hasDOI",
  "@type" : [ "http://www.w3.org/2002/07/owl#DatatypeProperty" ],
  "http://www.w3.org/2000/01/rdf-schema#comment" : [ {
    "@value" : "a Pub can have a DOI"
  } ],
  "http://www.w3.org/2000/01/rdf-schema#domain" : [ {
    "@id" : "http://www.semanticweb.org/badr/ontologies/2020/3/untitled-ontology-32#Publication"
  } ],
  "http://www.w3.org/2000/01/rdf-schema#range" : [ {
    "@id" : "http://www.w3.org/2001/XMLSchema#string"
  } ],
  "http://www.w3.org/2000/01/rdf-schema#subPropertyOf" : [ {
    "@id" : "http://www.w3.org/2002/07/owl#topDataProperty"
  } ]
}, {
  "@id" : "http://www.semanticweb.org/badr/ontologies/2020/3/untitled-ontology-32#hasDate",
  "@type" : [ "http://www.w3.org/2002/07/owl#DatatypeProperty", "http://www.w3.org/2002/07/owl#FunctionalProperty" ],
  "http://www.w3.org/2000/01/rdf-schema#comment" : [ {
    "@value" : "a Publication has a Date"
  } ],
  "http://www.w3.org/2000/01/rdf-schema#domain" : [ {
    "@id" : "http://www.semanticweb.org/badr/ontologies/2020/3/untitled-ontology-32#Publication"
  } ],
  "http://www.w3.org/2000/01/rdf-schema#range" : [ {
    "@id" : "http://www.w3.org/2001/XMLSchema#dateTime"
  } ],
  "http://www.w3.org/2000/01/rdf-schema#subPropertyOf" : [ {
    "@id" : "http://www.w3.org/2002/07/owl#topDataProperty"
  } ]
}, {
  "@id" : "http://www.semanticweb.org/badr/ontologies/2020/3/untitled-ontology-32#hasEndDate",
  "@type" : [ "http://www.w3.org/2002/07/owl#DatatypeProperty", "http://www.w3.org/2002/07/owl#FunctionalProperty" ],
  "http://www.w3.org/2000/01/rdf-schema#comment" : [ {
    "@value" : "a conference has Ende"
  } ],
  "http://www.w3.org/2000/01/rdf-schema#domain" : [ {
    "@id" : "http://www.semanticweb.org/badr/ontologies/2020/3/untitled-ontology-32#Conference"
  } ],
  "http://www.w3.org/2000/01/rdf-schema#range" : [ {
    "@id" : "http://www.w3.org/2001/XMLSchema#dateTime"
  } ],
  "http://www.w3.org/2000/01/rdf-schema#subPropertyOf" : [ {
    "@id" : "http://www.w3.org/2002/07/owl#topDataProperty"
  } ]
}, {
  "@id" : "http://www.semanticweb.org/badr/ontologies/2020/3/untitled-ontology-32#hasJournalName",
  "@type" : [ "http://www.w3.org/2002/07/owl#DatatypeProperty", "http://www.w3.org/2002/07/owl#FunctionalProperty" ],
  "http://www.w3.org/2000/01/rdf-schema#comment" : [ {
    "@value" : "a Journal has a Name"
  } ],
  "http://www.w3.org/2000/01/rdf-schema#domain" : [ {
    "@id" : "http://www.semanticweb.org/badr/ontologies/2020/3/untitled-ontology-32#Journal"
  } ],
  "http://www.w3.org/2000/01/rdf-schema#range" : [ {
    "@id" : "http://www.w3.org/2001/XMLSchema#string"
  } ],
  "http://www.w3.org/2000/01/rdf-schema#subPropertyOf" : [ {
    "@id" : "http://www.w3.org/2002/07/owl#topDataProperty"
  } ]
}, {
  "@id" : "http://www.semanticweb.org/badr/ontologies/2020/3/untitled-ontology-32#hasKey",
  "@type" : [ "http://www.w3.org/2002/07/owl#DatatypeProperty" ],
  "http://www.w3.org/2000/01/rdf-schema#comment" : [ {
    "@value" : "a Pub has a Key"
  } ],
  "http://www.w3.org/2000/01/rdf-schema#domain" : [ {
    "@id" : "http://www.semanticweb.org/badr/ontologies/2020/3/untitled-ontology-32#Publication"
  } ],
  "http://www.w3.org/2000/01/rdf-schema#range" : [ {
    "@id" : "http://www.w3.org/2001/XMLSchema#string"
  } ],
  "http://www.w3.org/2000/01/rdf-schema#subPropertyOf" : [ {
    "@id" : "http://www.w3.org/2002/07/owl#topDataProperty"
  } ]
}, {
  "@id" : "http://www.semanticweb.org/badr/ontologies/2020/3/untitled-ontology-32#hasLocationName",
  "@type" : [ "http://www.w3.org/2002/07/owl#DatatypeProperty", "http://www.w3.org/2002/07/owl#FunctionalProperty" ],
  "http://www.w3.org/2000/01/rdf-schema#comment" : [ {
    "@value" : "Location has a Name"
  } ],
  "http://www.w3.org/2000/01/rdf-schema#domain" : [ {
    "@id" : "http://www.semanticweb.org/badr/ontologies/2020/3/untitled-ontology-32#Conference"
  } ],
  "http://www.w3.org/2000/01/rdf-schema#range" : [ {
    "@id" : "http://www.w3.org/2001/XMLSchema#string"
  } ],
  "http://www.w3.org/2000/01/rdf-schema#subPropertyOf" : [ {
    "@id" : "http://www.w3.org/2002/07/owl#topDataProperty"
  } ]
}, {
  "@id" : "http://www.semanticweb.org/badr/ontologies/2020/3/untitled-ontology-32#hasMember",
  "@type" : [ "http://www.w3.org/2002/07/owl#ObjectProperty", "http://www.w3.org/2002/07/owl#AsymmetricProperty", "http://www.w3.org/2002/07/owl#IrreflexiveProperty" ],
  "http://www.w3.org/2000/01/rdf-schema#comment" : [ {
    "@value" : "Affiliation have afficated Person caller member"
  } ],
  "http://www.w3.org/2000/01/rdf-schema#domain" : [ {
    "@id" : "http://www.semanticweb.org/badr/ontologies/2020/3/untitled-ontology-32#Affiliation"
  } ],
  "http://www.w3.org/2000/01/rdf-schema#range" : [ {
    "@id" : "http://www.semanticweb.org/badr/ontologies/2020/3/untitled-ontology-32#Person"
  } ],
  "http://www.w3.org/2000/01/rdf-schema#subPropertyOf" : [ {
    "@id" : "http://www.w3.org/2002/07/owl#topObjectProperty"
  } ]
}, {
  "@id" : "http://www.semanticweb.org/badr/ontologies/2020/3/untitled-ontology-32#hasORCID",
  "@type" : [ "http://www.w3.org/2002/07/owl#DatatypeProperty", "http://www.w3.org/2002/07/owl#FunctionalProperty" ],
  "http://www.w3.org/2000/01/rdf-schema#domain" : [ {
    "@id" : "http://www.semanticweb.org/badr/ontologies/2020/3/untitled-ontology-32#Person"
  } ],
  "http://www.w3.org/2000/01/rdf-schema#range" : [ {
    "@id" : "http://www.w3.org/2001/XMLSchema#string"
  } ],
  "http://www.w3.org/2000/01/rdf-schema#subPropertyOf" : [ {
    "@id" : "http://www.w3.org/2002/07/owl#topDataProperty"
  } ]
}, {
  "@id" : "http://www.semanticweb.org/badr/ontologies/2020/3/untitled-ontology-32#hasParticipant",
  "@type" : [ "http://www.w3.org/2002/07/owl#ObjectProperty", "http://www.w3.org/2002/07/owl#AsymmetricProperty", "http://www.w3.org/2002/07/owl#IrreflexiveProperty" ],
  "http://www.w3.org/2000/01/rdf-schema#comment" : [ {
    "@value" : "a Conference has a Participant"
  } ],
  "http://www.w3.org/2000/01/rdf-schema#domain" : [ {
    "@id" : "http://www.semanticweb.org/badr/ontologies/2020/3/untitled-ontology-32#Conference"
  } ],
  "http://www.w3.org/2000/01/rdf-schema#range" : [ {
    "@id" : "http://www.semanticweb.org/badr/ontologies/2020/3/untitled-ontology-32#Person"
  } ],
  "http://www.w3.org/2000/01/rdf-schema#subPropertyOf" : [ {
    "@id" : "http://www.w3.org/2002/07/owl#topObjectProperty"
  } ],
  "http://www.w3.org/2002/07/owl#inverseOf" : [ {
    "@id" : "http://www.semanticweb.org/badr/ontologies/2020/3/untitled-ontology-32#isParticipantOf"
  } ]
}, {
  "@id" : "http://www.semanticweb.org/badr/ontologies/2020/3/untitled-ontology-32#hasPerson",
  "@type" : [ "http://www.w3.org/2002/07/owl#ObjectProperty", "http://www.w3.org/2002/07/owl#AsymmetricProperty", "http://www.w3.org/2002/07/owl#IrreflexiveProperty" ],
  "http://www.w3.org/2000/01/rdf-schema#comment" : [ {
    "@value" : "a Publication is Written by a Person"
  } ],
  "http://www.w3.org/2000/01/rdf-schema#domain" : [ {
    "@id" : "http://www.semanticweb.org/badr/ontologies/2020/3/untitled-ontology-32#Publication"
  } ],
  "http://www.w3.org/2000/01/rdf-schema#range" : [ {
    "@id" : "http://www.semanticweb.org/badr/ontologies/2020/3/untitled-ontology-32#Person"
  } ],
  "http://www.w3.org/2000/01/rdf-schema#subPropertyOf" : [ {
    "@id" : "http://www.w3.org/2002/07/owl#topObjectProperty"
  } ],
  "http://www.w3.org/2002/07/owl#inverseOf" : [ {
    "@id" : "http://www.semanticweb.org/badr/ontologies/2020/3/untitled-ontology-32#isOneOf"
  } ]
}, {
  "@id" : "http://www.semanticweb.org/badr/ontologies/2020/3/untitled-ontology-32#hasPublished",
  "@type" : [ "http://www.w3.org/2002/07/owl#ObjectProperty" ],
  "http://www.w3.org/2000/01/rdf-schema#domain" : [ {
    "@id" : "http://www.semanticweb.org/badr/ontologies/2020/3/untitled-ontology-32#Journal"
  } ],
  "http://www.w3.org/2000/01/rdf-schema#range" : [ {
    "@id" : "http://www.semanticweb.org/badr/ontologies/2020/3/untitled-ontology-32#Publication"
  } ],
  "http://www.w3.org/2000/01/rdf-schema#subPropertyOf" : [ {
    "@id" : "http://www.w3.org/2002/07/owl#topObjectProperty"
  } ],
  "http://www.w3.org/2002/07/owl#inverseOf" : [ {
    "@id" : "http://www.semanticweb.org/badr/ontologies/2020/3/untitled-ontology-32#isPublished"
  } ]
}, {
  "@id" : "http://www.semanticweb.org/badr/ontologies/2020/3/untitled-ontology-32#hasPublisherName",
  "@type" : [ "http://www.w3.org/2002/07/owl#DatatypeProperty", "http://www.w3.org/2002/07/owl#FunctionalProperty" ],
  "http://www.w3.org/2000/01/rdf-schema#domain" : [ {
    "@id" : "http://www.semanticweb.org/badr/ontologies/2020/3/untitled-ontology-32#publisher"
  } ],
  "http://www.w3.org/2000/01/rdf-schema#range" : [ {
    "@id" : "http://www.w3.org/2001/XMLSchema#string"
  } ],
  "http://www.w3.org/2000/01/rdf-schema#subPropertyOf" : [ {
    "@id" : "http://www.w3.org/2002/07/owl#topDataProperty"
  } ]
}, {
  "@id" : "http://www.semanticweb.org/badr/ontologies/2020/3/untitled-ontology-32#hasTitle",
  "@type" : [ "http://www.w3.org/2002/07/owl#DatatypeProperty", "http://www.w3.org/2002/07/owl#FunctionalProperty" ],
  "http://www.w3.org/2000/01/rdf-schema#domain" : [ {
    "@id" : "http://www.semanticweb.org/badr/ontologies/2020/3/untitled-ontology-32#Publication"
  } ],
  "http://www.w3.org/2000/01/rdf-schema#range" : [ {
    "@id" : "http://www.w3.org/2001/XMLSchema#string"
  } ],
  "http://www.w3.org/2000/01/rdf-schema#subPropertyOf" : [ {
    "@id" : "http://www.w3.org/2002/07/owl#topDataProperty"
  } ]
}, {
  "@id" : "http://www.semanticweb.org/badr/ontologies/2020/3/untitled-ontology-32#isOneOf",
  "@type" : [ "http://www.w3.org/2002/07/owl#ObjectProperty" ],
  "http://www.w3.org/2000/01/rdf-schema#comment" : [ {
    "@value" : ""
  }, {
    "@value" : "a publication was written by some person"
  } ],
  "http://www.w3.org/2000/01/rdf-schema#domain" : [ {
    "@id" : "http://www.semanticweb.org/badr/ontologies/2020/3/untitled-ontology-32#Person"
  } ],
  "http://www.w3.org/2000/01/rdf-schema#range" : [ {
    "@id" : "http://www.semanticweb.org/badr/ontologies/2020/3/untitled-ontology-32#Publication"
  } ],
  "http://www.w3.org/2000/01/rdf-schema#subPropertyOf" : [ {
    "@id" : "http://www.w3.org/2002/07/owl#topObjectProperty"
  } ]
}, {
  "@id" : "http://www.semanticweb.org/badr/ontologies/2020/3/untitled-ontology-32#isParticipantOf",
  "@type" : [ "http://www.w3.org/2002/07/owl#ObjectProperty", "http://www.w3.org/2002/07/owl#AsymmetricProperty", "http://www.w3.org/2002/07/owl#IrreflexiveProperty" ],
  "http://www.w3.org/2000/01/rdf-schema#comment" : [ {
    "@value" : "a Conference has a Person"
  } ],
  "http://www.w3.org/2000/01/rdf-schema#domain" : [ {
    "@id" : "http://www.semanticweb.org/badr/ontologies/2020/3/untitled-ontology-32#Conference"
  } ],
  "http://www.w3.org/2000/01/rdf-schema#range" : [ {
    "@id" : "http://www.semanticweb.org/badr/ontologies/2020/3/untitled-ontology-32#Person"
  } ],
  "http://www.w3.org/2000/01/rdf-schema#subPropertyOf" : [ {
    "@id" : "http://www.w3.org/2002/07/owl#topObjectProperty"
  } ],
  "http://www.w3.org/2002/07/owl#inverseOf" : [ {
    "@id" : "http://www.semanticweb.org/badr/ontologies/2020/3/untitled-ontology-32#isParticipantOf"
  } ]
}, {
  "@id" : "http://www.semanticweb.org/badr/ontologies/2020/3/untitled-ontology-32#isPublished",
  "@type" : [ "http://www.w3.org/2002/07/owl#ObjectProperty", "http://www.w3.org/2002/07/owl#AsymmetricProperty", "http://www.w3.org/2002/07/owl#IrreflexiveProperty" ],
  "http://www.w3.org/2000/01/rdf-schema#domain" : [ {
    "@id" : "http://www.semanticweb.org/badr/ontologies/2020/3/untitled-ontology-32#Publication"
  } ],
  "http://www.w3.org/2000/01/rdf-schema#range" : [ {
    "@id" : "http://www.semanticweb.org/badr/ontologies/2020/3/untitled-ontology-32#Journal"
  } ],
  "http://www.w3.org/2000/01/rdf-schema#subPropertyOf" : [ {
    "@id" : "http://www.w3.org/2002/07/owl#topObjectProperty"
  } ]
}, {
  "@id" : "http://www.semanticweb.org/badr/ontologies/2020/3/untitled-ontology-32#isPublisherOf",
  "@type" : [ "http://www.w3.org/2002/07/owl#ObjectProperty", "http://www.w3.org/2002/07/owl#InverseFunctionalProperty", "http://www.w3.org/2002/07/owl#AsymmetricProperty", "http://www.w3.org/2002/07/owl#IrreflexiveProperty" ],
  "http://www.w3.org/2000/01/rdf-schema#comment" : [ {
    "@value" : "A publisher is the publisher of a journal"
  } ],
  "http://www.w3.org/2000/01/rdf-schema#domain" : [ {
    "@id" : "http://www.semanticweb.org/badr/ontologies/2020/3/untitled-ontology-32#publisher"
  } ],
  "http://www.w3.org/2000/01/rdf-schema#range" : [ {
    "@id" : "http://www.semanticweb.org/badr/ontologies/2020/3/untitled-ontology-32#Journal"
  } ],
  "http://www.w3.org/2000/01/rdf-schema#subPropertyOf" : [ {
    "@id" : "http://www.w3.org/2002/07/owl#topObjectProperty"
  } ]
}, {
  "@id" : "http://www.semanticweb.org/badr/ontologies/2020/3/untitled-ontology-32#publisher",
  "@type" : [ "http://www.w3.org/2002/07/owl#Class" ],
  "http://www.w3.org/2000/01/rdf-schema#comment" : [ {
    "@value" : "publisher  is a Company"
  } ],
  "http://www.w3.org/2000/01/rdf-schema#subClassOf" : [ {
    "@id" : "_:genid21"
  }, {
    "@id" : "_:genid22"
  } ]
} ]